ibish/__init__.py
ibish/compiler.py
ibish-1.0.4.dist-info/LICENSE
ibish-1.0.4.dist-info/METADATA
ibish-1.0.4.dist-info/WHEEL
ibish-1.0.4.dist-info/entry_points.txt
ibish-1.0.4.dist-info/RECORD
